biophony/__init__.py
biophony/align.py
biophony/align_gen.py
biophony/align_seq_item.py
biophony/bed_gen.py
biophony/bio_read.py
biophony/bio_read_gen.py
biophony/bio_seq.py
biophony/bio_seq_gen.py
biophony/bio_seq_var_gen.py
biophony/const.py
biophony/cov_gen.py
biophony/elem_seq.py
biophony/elem_seq_gen.py
biophony/elem_seq_var_gen.py
biophony/elements.py
biophony/fasta_writer.py
biophony/fastq_writer.py
biophony/gen_bed.py
biophony/gen_cov.py
biophony/gen_fasta.py
biophony/gen_fastavar.py
biophony/gen_fastq.py
biophony/gen_sam.py
biophony/gen_vcf.py
biophony/logger.py
biophony/main.py
biophony/mutsim.py
biophony/prg.py
biophony/py.typed
biophony/range.py
biophony/read_group.py
biophony/sam_file.py
biophony/variant_maker.py
biophony-1.5.0.dist-info/METADATA
biophony-1.5.0.dist-info/WHEEL
biophony-1.5.0.dist-info/entry_points.txt
biophony-1.5.0.dist-info/RECORD
