Metadata-Version: 2.3
Name: biophony
Version: 1.5.0
Summary: Random generation of genetic files
License: CeCILL
Keywords: CNRGH,genomic,gene,genetic,mutation,VCF,BED,FASTA,coverage
Author: Pierrick ROGER
Author-email: pierrick.roger@cea.fr
Requires-Python: >=3.11
Classifier: Programming Language :: Python :: 3
Classifier: License :: CeCILL-C Free Software License Agreement (CECILL-C)
Classifier: Operating System :: OS Independent
Requires-Dist: colorlog (>=6.9.0)
Requires-Dist: mutation-simulator (>=3.0.2)
Requires-Dist: rich-argparse (>=1.6.0,<2.0.0)
Project-URL: Bug Tracker, https://gitlab.com/cnrgh/databases/biophony/issues
Project-URL: Changelog, https://gitlab.com/cnrgh/databases/biophony/-/blob/main/CHANGELOG.md
Project-URL: Documentation, https://cnrgh.gitlab.io/databases/biophony/
Project-URL: Homepage, https://gitlab.com/cnrgh/databases/biophony
Project-URL: Repository, https://gitlab.com/cnrgh/databases/biophony
